NekoMimi/__init__.py
NekoMimi/__main__.py
NekoMimi/colourimi.py
NekoMimi/consoleToys.py
NekoMimi/reg.py
NekoMimi/utils.py
NekoMimi/legacy/__init__.py
NekoMimi/legacy/colourimi.py
NekoMimi/legacy/consoleToys.py
NekoMimi/legacy/tools.py
NekoMimi-1.3.1.dist-info/LICENSE
NekoMimi-1.3.1.dist-info/METADATA
NekoMimi-1.3.1.dist-info/WHEEL
NekoMimi-1.3.1.dist-info/top_level.txt
NekoMimi-1.3.1.dist-info/RECORD
