Metadata-Version: 2.1
Name: NekoMimi
Version: 1.3.1
Summary: Multi-Tool of macros to facilitate development
Home-page: https://github.com/NekoMimiOffical/NekoMimi
Author: NekoMimiOffical
Author-email: nekomimi@tilde.team
License: Apache2
Project-URL: Bug Tracker, https://github.com/NekoMimiOffical/NekoMimi/issues
Classifier: Programming Language :: Python :: 3
Classifier: Operating System :: OS Independent
Requires-Python: >=3.10
License-File: LICENSE
Requires-Dist: aiohttp
Requires-Dist: requests
Requires-Dist: pyfiglet
